self_limiters-0.4.0.dist-info/METADATA
self_limiters-0.4.0.dist-info/WHEEL
self_limiters-0.4.0.dist-info/license_files/LICENSE
self_limiters/__init__.py
self_limiters/__init__.pyi
self_limiters/py.typed
self_limiters/self_limiters.pyd
self_limiters-0.4.0.dist-info/RECORD
