Metadata-Version: 2.1
Name: self-limiters
Version: 0.4.0
Classifier: Development Status :: 4 - Beta
Classifier: Programming Language :: Rust
Classifier: Programming Language :: Python
Classifier: Programming Language :: Python :: 3.9
Classifier: Programming Language :: Python :: 3.10
Classifier: Programming Language :: Python :: 3.11
Classifier: Programming Language :: Python :: Implementation :: CPython
Classifier: Programming Language :: Python :: Implementation :: PyPy
Classifier: License :: OSI Approved :: BSD License
Classifier: Intended Audience :: Developers
License-File: LICENSE
Summary: Distributed async rate limiters, using Redis
Keywords: distributed,async,rate-limit,rate,limit,limiting,redis,rust,semaphore,token,leaky,bucket,tokenbucket
Author-email: Sondre Lillebø Gundersen <sondrelg@live.no>
Requires-Python: >=3.9
Project-URL: releases, https://github.com/sondrelg/self-limiters/releases
